Metadata-Version: 2.1
Name: pytube-lanuma
Version: 15.2.3
Summary: Python 3 library for downloading YouTube Videos.
Home-page: https://github.com/lanuma/pytube-lanuma
Author: Angga Lanuma
Author-email: lanuma.angga@gmail.com
License: MIT
Project-URL: Bug Reports, https://github.com/lanuma/pytube-lanuma/issues
Project-URL: Read the Docs, https://pytube.io
Keywords: youtube,download,video,stream
Classifier: Development Status :: 5 - Production/Stable
Classifier: Environment :: Console
Classifier: Intended Audience :: Developers
Classifier: License :: OSI Approved :: MIT License
Classifier: Natural Language :: English
Classifier: Operating System :: OS Independent
Classifier: Programming Language :: Python :: 3.7
Classifier: Programming Language :: Python :: 3.8
Classifier: Programming Language :: Python :: 3.9
Classifier: Programming Language :: Python :: 3.10
Classifier: Programming Language :: Python :: 3.11
Classifier: Programming Language :: Python
Classifier: Topic :: Internet
Classifier: Topic :: Multimedia :: Video
Classifier: Topic :: Software Development :: Libraries :: Python Modules
Classifier: Topic :: Terminals
Classifier: Topic :: Utilities
Requires-Python: >=3.7
License-File: LICENSE
